greenery/__init__.py
greenery/bound.py
greenery/bound_test.py
greenery/charclass.py
greenery/charclass_test.py
greenery/conc_test.py
greenery/fsm.py
greenery/fsm_test.py
greenery/mult_test.py
greenery/multiplier.py
greenery/multiplier_test.py
greenery/parse.py
greenery/parse_test.py
greenery/pattern_test.py
greenery/rxelems.py
greenery/rxelems_test.py
greenery-4.2.2.dist-info/LICENSE.txt
greenery-4.2.2.dist-info/METADATA
greenery-4.2.2.dist-info/WHEEL
greenery-4.2.2.dist-info/top_level.txt
greenery-4.2.2.dist-info/RECORD
